{
  "name_hebrew": "קוקלות",
  "ingredients": [
    "ביצים",
    "סולת",
    "שמן,",
    "מלח",
    "פ. שחור",
    "פפריקה",
    "מים",
    "כפית א. אפיה"
  ],
  "instructions": [
    "שמים בצלחת עמוקה ביצה",
    "מוסיפים לה מעט שמן, מים ותבלינים",
    "מוסיפים סולת לאט לאט עד שאפשר ללוש את זה",
    "עושים עיגולים וזורקים לתוך החמין",
    "בתאבון\\!\\!\\!"
  ],
  "metadata": {
    "source_file": "safed_some.md",
    "original_text_block": "שם המתכון: קוקלות\n\nרשימת מצרכים:\n\nביצים\n\nסולת\n\nשמן,\n\nמלח\n\nפ. שחור\n\nפפריקה\n\nמים\n\nכפית א. אפיה\n\nאופן ההכנה:\n\nשמים בצלחת עמוקה ביצה\n\nמוסיפים לה מעט שמן, מים ותבלינים\n\nמוסיפים סולת לאט לאט עד שאפשר ללוש את זה\n\nעושים עיגולים וזורקים לתוך החמין\n\nבתאבון\\!\\!\\!\n\n"
  },
  "id": "קוקלות"
}