{
  "name": "Biscoti Judy",
  "ingredients": [
    "1 cup of oil",
    "1 cup of sugar",
    "1 cup Brown sugar",
    "2 tsp of Vanilla extract",
    "3 cups of flour",
    "1 tsp Baking Soda",
    "1 tsp Salt",
    "1 pack or 1 cup chocolate Chips"
  ],
  "instructions": [
    "Heat oven 350-180",
    "Mix all the ingredients except the chocolate chips.",
    "Add the chocolate chips and don't be alarmed if the dough comes out crumbly, that's how it should be...",
    "Make two rolls from the dough or more if you want, bake for about twenty minutes to half an hour until golden.",
    "Cool a little and cut into slices while it's still a little warm"
  ],
  "serves": "",
  "source": "recime_raw"
}